nonebot_plugin_AutoRepeater/__init__.py
nonebot_plugin_AutoRepeater/config.py
nonebot_plugin_AutoRepeater/data_source.py
nonebot_plugin_AutoRepeater-0.1.4.dist-info/LICENSE
nonebot_plugin_AutoRepeater-0.1.4.dist-info/METADATA
nonebot_plugin_AutoRepeater-0.1.4.dist-info/WHEEL
nonebot_plugin_AutoRepeater-0.1.4.dist-info/top_level.txt
nonebot_plugin_AutoRepeater-0.1.4.dist-info/RECORD
