Metadata-Version: 2.1
Name: nonebot-plugin-AutoRepeater
Version: 0.1.4
Summary: A plugin based on NoneBot2, auto repeater message in group.
Home-page: https://github.com/DMCSWCG/nonebot-plugin-AutoRepeater
Author: DMCSWCG
License: UNKNOWN
Project-URL: Bug Tracker, https://github.com/DMCSWCG/nonebot-plugin-AutoRepeater/issues
Platform: UNKNOWN
Classifier: Programming Language :: Python :: 3
Classifier: License :: OSI Approved :: GNU General Public License v3 (GPLv3)
Classifier: Operating System :: OS Independent
Requires-Python: >=3.7
Requires-Dist: nonebot2 (>=2.0.0rc1)
Requires-Dist: nonebot-adapter-onebot (>=2.0.0rc1)
Requires-Dist: nonebot-plugin-apscheduler
Requires-Dist: aiofiles
Requires-Dist: pydantic
Requires-Dist: httpx
Requires-Dist: ujson
